{
  "suite": "bid128_to_int8_xrnint",
  "group": "decimal128_operations",
  "format": "decimal128",
  "header": "third_party/intel_dfp/TESTS/readtest.h",
  "source": "third_party/intel_dfp/TESTS/readtest.in",
  "function": "bid128_to_int8_xrnint",
  "kind": "unary_op",
  "output_type": "OP_INT8",
  "input_types": [
    "OP_DEC128"
  ],
  "compare_group": "CMP_FUZZYSTATUS",
  "cases": [
    {"id":"bid128_to_int8_xrnint_23370","line":31289,"operands":["[0001ed09bead87c0378d8e62ffffffff]"],"expected":"0","status":"20","rounding":0},
    {"id":"bid128_to_int8_xrnint_23371","line":31290,"operands":["[0001ed09bead87c0378d8e64ffffffff]"],"expected":"0","status":"00","rounding":0},
    {"id":"bid128_to_int8_xrnint_23372","line":31291,"operands":["0.5"],"expected":"0","status":"20","rounding":0},
    {"id":"bid128_to_int8_xrnint_23373","line":31292,"operands":["1.0"],"expected":"1","status":"00","rounding":0},
    {"id":"bid128_to_int8_xrnint_23374","line":31293,"operands":["1073741824"],"expected":"-128","status":"01","rounding":0},
    {"id":"bid128_to_int8_xrnint_23375","line":31294,"operands":["-1"],"expected":"-1","status":"00","rounding":0},
    {"id":"bid128_to_int8_xrnint_23376","line":31295,"operands":["1"],"expected":"1","status":"00","rounding":0},
    {"id":"bid128_to_int8_xrnint_23377","line":31296,"operands":["129"],"expected":"-128","status":"01","rounding":0},
    {"id":"bid128_to_int8_xrnint_23378","line":31297,"operands":["[15a1a020d9d08862,ffffffffffffffff]"],"expected":"0","status":"20","rounding":0},
    {"id":"bid128_to_int8_xrnint_23379","line":31298,"operands":["2147483648"],"expected":"-128","status":"01","rounding":0},
    {"id":"bid128_to_int8_xrnint_23380","line":31299,"operands":["[2FFCF684DF56C3E01BC6C73200000000]"],"expected":"0","status":"20","rounding":0},
    {"id":"bid128_to_int8_xrnint_23381","line":31300,"operands":["[2FFDEC8B86EF679D76FC433D80000000]"],"expected":"1","status":"20","rounding":0},
    {"id":"bid128_to_int8_xrnint_23382","line":31302,"operands":["[2FFE49F4A966D45CD522088F00000000]"],"expected":"2","status":"20","rounding":0},
    {"id":"bid128_to_int8_xrnint_23383","line":31303,"operands":["[30023E5E8B72E12C27CBA28640000000]"],"expected":"126","status":"20","rounding":0},
    {"id":"bid128_to_int8_xrnint_23384","line":31304,"operands":["[30023E9DA751F13D8814481980000000]"],"expected":"127","status":"00","rounding":0},
    {"id":"bid128_to_int8_xrnint_23385","line":31305,"operands":["[30023EDCC331014EE85CEDACC0000000]"],"expected":"-128","status":"01","rounding":0},
    {"id":"bid128_to_int8_xrnint_23386","line":31306,"operands":["[30023F1BDF10116048A5934000000000]"],"expected":"-128","status":"01","rounding":0},
    {"id":"bid128_to_int8_xrnint_23387","line":31307,"operands":["[30023F5AFAEF2171A8EE38D340000000]"],"expected":"-128","status":"01","rounding":0},
    {"id":"bid128_to_int8_xrnint_23388","line":31308,"operands":["[30023F9A16CE31830936DE6680000000]"],"expected":"-128","status":"01","rounding":0},
    {"id":"bid128_to_int8_xrnint_23389","line":31309,"operands":["[30027DB98662029DD0B9DB5980000000]"],"expected":"-128","status":"01","rounding":0},
    {"id":"bid128_to_int8_xrnint_23390","line":31310,"operands":["[30027DF8A24112AF310280ECC0000000]"],"expected":"-128","status":"01","rounding":0},
    {"id":"bid128_to_int8_xrnint_23391","line":31311,"operands":["[30027E37BE2022C0914B268000000000]"],"expected":"-128","status":"01","rounding":0},
    {"id":"bid128_to_int8_xrnint_23392","line":31312,"operands":["[30027E76D9FF32D1F193CC1340000000]"],"expected":"-128","status":"01","rounding":0},
    {"id":"bid128_to_int8_xrnint_23393","line":31313,"operands":["[30027EB5F5DE42E351DC71A680000000]"],"expected":"-128","status":"01","rounding":0},
    {"id":"bid128_to_int8_xrnint_23394","line":31315,"operands":["[300294286EACB8CB0A8CB6B140000000]"],"expected":"-128","status":"01","rounding":0},
    {"id":"bid128_to_int8_xrnint_23395","line":31316,"operands":["[301c000000000000,0820400401020001]"],"expected":"1","status":"20","rounding":0},
    {"id":"bid128_to_int8_xrnint_23396","line":31317,"operands":["[303A00000000000000000000000003E7]"],"expected":"1","status":"20","rounding":0},
    {"id":"bid128_to_int8_xrnint_23397","line":31318,"operands":["[303E0000000000000000000000000005]"],"expected":"0","status":"20","rounding":0},
    {"id":"bid128_to_int8_xrnint_23398","line":31319,"operands":["[303E000000000000000000000000000F]"],"expected":"2","status":"20","rounding":0},
    {"id":"bid128_to_int8_xrnint_23399","line":31320,"operands":["[303E00000000000000000000000004F1]"],"expected":"126","status":"20","rounding":0},
    {"id":"bid128_to_int8_xrnint_23400","line":31321,"operands":["[303E00000000000000000000000004FB]"],"expected":"-128","status":"01","rounding":0},
    {"id":"bid128_to_int8_xrnint_23401","line":31322,"operands":["[303E0000000000000000000000000505]"],"expected":"-128","status":"01","rounding":0},
    {"id":"bid128_to_int8_xrnint_23402","line":31323,"operands":["[303E00000000000000000000000009FB]"],"expected":"-128","status":"01","rounding":0},
    {"id":"bid128_to_int8_xrnint_23403","line":31324,"operands":["[303E0000000000000000000000000A05]"],"expected":"-128","status":"01","rounding":0},
    {"id":"bid128_to_int8_xrnint_23404","line":31325,"operands":["[303E0000000000000000000000000BBD]"],"expected":"-128","status":"01","rounding":0},
    {"id":"bid128_to_int8_xrnint_23405","line":31327,"operands":["[3040000000000000000000000000007F]"],"expected":"127","status":"00","rounding":0},
    {"id":"bid128_to_int8_xrnint_23406","line":31328,"operands":["[30400000000000000000000000000080]"],"expected":"-128","status":"01","rounding":0},
    {"id":"bid128_to_int8_xrnint_23407","line":31329,"operands":["[30400000000000000000000000000081]"],"expected":"-128","status":"01","rounding":0},
    {"id":"bid128_to_int8_xrnint_23408","line":31330,"operands":["[304000000000000000000000000000FF]"],"expected":"-128","status":"01","rounding":0},
    {"id":"bid128_to_int8_xrnint_23409","line":31331,"operands":["[30400000000000000000000000000100]"],"expected":"-128","status":"01","rounding":0},
    {"id":"bid128_to_int8_xrnint_23410","line":31332,"operands":["[30400000000000000000000000000101]"],"expected":"-128","status":"01","rounding":0},
    {"id":"bid128_to_int8_xrnint_23411","line":31333,"operands":["[3041ED09BEAD87C0378D8E6400000000]"],"expected":"0","status":"00","rounding":0},
    {"id":"bid128_to_int8_xrnint_23412","line":31335,"operands":["5.05"],"expected":"5","status":"20","rounding":0},
    {"id":"bid128_to_int8_xrnint_23413","line":31336,"operands":["5.5"],"expected":"6","status":"20","rounding":0},
    {"id":"bid128_to_int8_xrnint_23414","line":31337,"operands":["[78000000000000000000000000000000]"],"expected":"-128","status":"01","rounding":0},
    {"id":"bid128_to_int8_xrnint_23415","line":31338,"operands":["[7c000000000000000000000000000000]"],"expected":"-128","status":"01","rounding":0},
    {"id":"bid128_to_int8_xrnint_23416","line":31339,"operands":["[7c003fffffffffff38c15b08ffffffff]"],"expected":"-128","status":"01","rounding":0},
    {"id":"bid128_to_int8_xrnint_23417","line":31340,"operands":["[7c003fffffffffff38c15b0affffffff]"],"expected":"-128","status":"01","rounding":0},
    {"id":"bid128_to_int8_xrnint_23418","line":31341,"operands":["[7e000000000000000000000000000000]"],"expected":"-128","status":"01","rounding":0},
    {"id":"bid128_to_int8_xrnint_23419","line":31342,"operands":["-9"],"expected":"-9","status":"00","rounding":0}
  ]
}
