{
  "suite": "bid32_to_uint64_floor",
  "group": "decimal32_operations",
  "format": "decimal32",
  "header": "third_party/intel_dfp/TESTS/readtest.h",
  "source": "third_party/intel_dfp/TESTS/readtest.in",
  "function": "bid32_to_uint64_floor",
  "kind": "unary_op",
  "output_type": "OP_BID_UINT64",
  "input_types": [
    "OP_DEC32"
  ],
  "compare_group": "CMP_FUZZYSTATUS",
  "cases": [
    {"id":"bid32_to_uint64_floor_22720","line":62849,"operands":["[2F4C4B40]"],"expected":"0","status":"00","rounding":0},
    {"id":"bid32_to_uint64_floor_22721","line":62851,"operands":["[2F96E360]"],"expected":"1","status":"00","rounding":0},
    {"id":"bid32_to_uint64_floor_22722","line":62853,"operands":["[30ADDA48]"],"expected":"300","status":"00","rounding":0},
    {"id":"bid32_to_uint64_floor_22723","line":62854,"operands":["[310003E7]"],"expected":"0","status":"00","rounding":0},
    {"id":"bid32_to_uint64_floor_22724","line":62855,"operands":["[32000005]"],"expected":"0","status":"00","rounding":0},
    {"id":"bid32_to_uint64_floor_22725","line":62856,"operands":["[3200000F]"],"expected":"1","status":"00","rounding":0},
    {"id":"bid32_to_uint64_floor_22726","line":62857,"operands":["[32000BBD]"],"expected":"300","status":"00","rounding":0},
    {"id":"bid32_to_uint64_floor_22727","line":62863,"operands":["[349E8480]"],"expected":"20000000000","status":"00","rounding":0},
    {"id":"bid32_to_uint64_floor_22728","line":62864,"operands":["[349E8480]"],"expected":"20000000000","status":"00","rounding":0},
    {"id":"bid32_to_uint64_floor_22729","line":62865,"operands":["[349E8480]"],"expected":"20000000000","status":"00","rounding":0},
    {"id":"bid32_to_uint64_floor_22730","line":62866,"operands":["[349E8480]"],"expected":"20000000000","status":"00","rounding":0},
    {"id":"bid32_to_uint64_floor_22731","line":62867,"operands":["[349E8480]"],"expected":"20000000000","status":"00","rounding":0},
    {"id":"bid32_to_uint64_floor_22732","line":62868,"operands":["[349E8480]"],"expected":"20000000000","status":"00","rounding":0},
    {"id":"bid32_to_uint64_floor_22733","line":62869,"operands":["[3635AFE5]"],"expected":"35184370000000","status":"00","rounding":0},
    {"id":"bid32_to_uint64_floor_22734","line":62870,"operands":["[3635AFE5]"],"expected":"35184370000000","status":"00","rounding":0},
    {"id":"bid32_to_uint64_floor_22735","line":62874,"operands":["[371E8480]"],"expected":"2000000000000000","status":"00","rounding":0},
    {"id":"bid32_to_uint64_floor_22736","line":62875,"operands":["[371E8480]"],"expected":"2000000000000000","status":"00","rounding":0},
    {"id":"bid32_to_uint64_floor_22737","line":62876,"operands":["[371E8480]"],"expected":"2000000000000000","status":"00","rounding":0},
    {"id":"bid32_to_uint64_floor_22738","line":62877,"operands":["[371E8480]"],"expected":"2000000000000000","status":"00","rounding":0},
    {"id":"bid32_to_uint64_floor_22739","line":62878,"operands":["[371E8480]"],"expected":"2000000000000000","status":"00","rounding":0},
    {"id":"bid32_to_uint64_floor_22740","line":62879,"operands":["[371E8480]"],"expected":"2000000000000000","status":"00","rounding":0},
    {"id":"bid32_to_uint64_floor_22741","line":62881,"operands":["[37800002]"],"expected":"20000000000","status":"00","rounding":0},
    {"id":"bid32_to_uint64_floor_22742","line":62882,"operands":["[37800002]"],"expected":"20000000000","status":"00","rounding":0},
    {"id":"bid32_to_uint64_floor_22743","line":62883,"operands":["[37800002]"],"expected":"20000000000","status":"00","rounding":0},
    {"id":"bid32_to_uint64_floor_22744","line":62884,"operands":["[37800002]"],"expected":"20000000000","status":"00","rounding":0},
    {"id":"bid32_to_uint64_floor_22745","line":62885,"operands":["[37800002]"],"expected":"20000000000","status":"00","rounding":0},
    {"id":"bid32_to_uint64_floor_22746","line":62886,"operands":["[37800002]"],"expected":"20000000000","status":"00","rounding":0},
    {"id":"bid32_to_uint64_floor_22747","line":62888,"operands":["[390F4240]"],"expected":"10000000000000000000","status":"00","rounding":0},
    {"id":"bid32_to_uint64_floor_22748","line":62889,"operands":["[3916E360]"],"expected":"15000000000000000000","status":"00","rounding":0},
    {"id":"bid32_to_uint64_floor_22749","line":62890,"operands":["[391C25C2]"],"expected":"18446740000000000000","status":"00","rounding":0},
    {"id":"bid32_to_uint64_floor_22750","line":62891,"operands":["[391C25C2]"],"expected":"18446740000000000000","status":"00","rounding":0},
    {"id":"bid32_to_uint64_floor_22751","line":62892,"operands":["[391C25C2]"],"expected":"18446740000000000000","status":"00","rounding":0},
    {"id":"bid32_to_uint64_floor_22752","line":62893,"operands":["[391C25C2]"],"expected":"18446740000000000000","status":"00","rounding":0},
    {"id":"bid32_to_uint64_floor_22753","line":62894,"operands":["[391C25C2]"],"expected":"18446740000000000000","status":"00","rounding":0},
    {"id":"bid32_to_uint64_floor_22754","line":62896,"operands":["[392625A0]"],"expected":"9223372036854775808","status":"01","rounding":0},
    {"id":"bid32_to_uint64_floor_22755","line":62899,"operands":["[3A000002]"],"expected":"2000000000000000","status":"00","rounding":0},
    {"id":"bid32_to_uint64_floor_22756","line":62900,"operands":["[3A000002]"],"expected":"2000000000000000","status":"00","rounding":0},
    {"id":"bid32_to_uint64_floor_22757","line":62901,"operands":["[3A000002]"],"expected":"2000000000000000","status":"00","rounding":0},
    {"id":"bid32_to_uint64_floor_22758","line":62902,"operands":["[3A000002]"],"expected":"2000000000000000","status":"00","rounding":0},
    {"id":"bid32_to_uint64_floor_22759","line":62903,"operands":["[3A000002]"],"expected":"2000000000000000","status":"00","rounding":0},
    {"id":"bid32_to_uint64_floor_22760","line":62904,"operands":["[3A000002]"],"expected":"2000000000000000","status":"00","rounding":0},
    {"id":"bid32_to_uint64_floor_22761","line":62905,"operands":["[3B80000F]"],"expected":"15000000000000000000","status":"00","rounding":0},
    {"id":"bid32_to_uint64_floor_22762","line":62906,"operands":["[3B800019]"],"expected":"9223372036854775808","status":"01","rounding":0},
    {"id":"bid32_to_uint64_floor_22763","line":62908,"operands":["[3C000001]"],"expected":"10000000000000000000","status":"00","rounding":0},
    {"id":"bid32_to_uint64_floor_22764","line":62911,"operands":["[6BD86F70]"],"expected":"0","status":"00","rounding":0},
    {"id":"bid32_to_uint64_floor_22765","line":62912,"operands":["[6CB89680]"],"expected":"0","status":"00","rounding":0},
    {"id":"bid32_to_uint64_floor_22766","line":62913,"operands":["[6E2CBCCC]"],"expected":"9223372000000000000","status":"00","rounding":0},
    {"id":"bid32_to_uint64_floor_22767","line":62914,"operands":["[6E2CBCCC]"],"expected":"9223372000000000000","status":"00","rounding":0},
    {"id":"bid32_to_uint64_floor_22768","line":62915,"operands":["[6E2CBCCC]"],"expected":"9223372000000000000","status":"00","rounding":0},
    {"id":"bid32_to_uint64_floor_22769","line":62916,"operands":["[6E2CBCCC]"],"expected":"9223372000000000000","status":"00","rounding":0},
    {"id":"bid32_to_uint64_floor_22770","line":62917,"operands":["[6E2CBCCC]"],"expected":"9223372000000000000","status":"00","rounding":0},
    {"id":"bid32_to_uint64_floor_22771","line":62918,"operands":["[6E2CBCCC]"],"expected":"9223372000000000000","status":"00","rounding":0},
    {"id":"bid32_to_uint64_floor_22772","line":62919,"operands":["[78000000]"],"expected":"9223372036854775808","status":"01","rounding":0},
    {"id":"bid32_to_uint64_floor_22773","line":62920,"operands":["[7c000000]"],"expected":"9223372036854775808","status":"01","rounding":0},
    {"id":"bid32_to_uint64_floor_22774","line":62921,"operands":["[7e000000]"],"expected":"9223372036854775808","status":"01","rounding":0},
    {"id":"bid32_to_uint64_floor_22775","line":62922,"operands":["9.223372E+18"],"expected":"9223372000000000000","status":"00","rounding":0},
    {"id":"bid32_to_uint64_floor_22776","line":95267,"operands":["[c2922102]"],"expected":"9223372036854775808","status":"01","rounding":0}
  ]
}
