{
  "suite": "bid32_llround",
  "group": "decimal32_operations",
  "format": "decimal32",
  "header": "third_party/intel_dfp/TESTS/readtest.h",
  "source": "third_party/intel_dfp/TESTS/readtest.in",
  "function": "bid32_llround",
  "kind": "unary_op",
  "output_type": "OP_INT64",
  "input_types": [
    "OP_DEC32"
  ],
  "compare_group": "CMP_FUZZYSTATUS",
  "cases": [
    {"id":"bid32_llround_52521","line":47168,"operands":["[2F4C4B40]"],"expected":"1","status":"00","rounding":0},
    {"id":"bid32_llround_52522","line":47170,"operands":["[2F96E360]"],"expected":"2","status":"00","rounding":0},
    {"id":"bid32_llround_52523","line":47172,"operands":["[30ADDA48]"],"expected":"301","status":"00","rounding":0},
    {"id":"bid32_llround_52524","line":47173,"operands":["[310003E7]"],"expected":"1","status":"00","rounding":0},
    {"id":"bid32_llround_52525","line":47174,"operands":["[310005DC]"],"expected":"2","status":"00","rounding":0},
    {"id":"bid32_llround_52526","line":47175,"operands":["[310495D4]"],"expected":"301","status":"00","rounding":0},
    {"id":"bid32_llround_52527","line":47176,"operands":["[31800096]"],"expected":"2","status":"00","rounding":0},
    {"id":"bid32_llround_52528","line":47177,"operands":["[31807562]"],"expected":"301","status":"00","rounding":0},
    {"id":"bid32_llround_52529","line":47178,"operands":["[32000005]"],"expected":"1","status":"00","rounding":0},
    {"id":"bid32_llround_52530","line":47179,"operands":["[3200000F]"],"expected":"2","status":"00","rounding":0},
    {"id":"bid32_llround_52531","line":47181,"operands":["[32000BBD]"],"expected":"301","status":"00","rounding":0},
    {"id":"bid32_llround_52532","line":47186,"operands":["[3420C49C]"],"expected":"2147484000","status":"00","rounding":0},
    {"id":"bid32_llround_52533","line":47188,"operands":["[34418937]"],"expected":"4294967000","status":"00","rounding":0},
    {"id":"bid32_llround_52534","line":47196,"operands":["[3916E360]"],"expected":"-9223372036854775808","status":"01","rounding":0},
    {"id":"bid32_llround_52535","line":47197,"operands":["[391C25C2]"],"expected":"-9223372036854775808","status":"01","rounding":0},
    {"id":"bid32_llround_52536","line":47199,"operands":["[392625A0]"],"expected":"-9223372036854775808","status":"01","rounding":0},
    {"id":"bid32_llround_52537","line":47202,"operands":["[3B80000F]"],"expected":"-9223372036854775808","status":"01","rounding":0},
    {"id":"bid32_llround_52538","line":47203,"operands":["[3B800019]"],"expected":"-9223372036854775808","status":"01","rounding":0},
    {"id":"bid32_llround_52539","line":47207,"operands":["[6BD86F70]"],"expected":"1","status":"00","rounding":0},
    {"id":"bid32_llround_52540","line":47208,"operands":["[6E2CBCCC]"],"expected":"9223372000000000000","status":"00","rounding":0},
    {"id":"bid32_llround_52541","line":47209,"operands":["[AF4C4B40]"],"expected":"-1","status":"00","rounding":0},
    {"id":"bid32_llround_52542","line":47210,"operands":["[AF8F4240]"],"expected":"-1","status":"00","rounding":0},
    {"id":"bid32_llround_52543","line":47211,"operands":["[AF96E360]"],"expected":"-2","status":"00","rounding":0},
    {"id":"bid32_llround_52544","line":47212,"operands":["[B0ADC6C0]"],"expected":"-300","status":"00","rounding":0},
    {"id":"bid32_llround_52545","line":47213,"operands":["[B0ADDA48]"],"expected":"-301","status":"00","rounding":0},
    {"id":"bid32_llround_52546","line":47214,"operands":["[B10003E7]"],"expected":"-1","status":"00","rounding":0},
    {"id":"bid32_llround_52547","line":47215,"operands":["[B10005DC]"],"expected":"-2","status":"00","rounding":0},
    {"id":"bid32_llround_52548","line":47216,"operands":["[B10495D4]"],"expected":"-301","status":"00","rounding":0},
    {"id":"bid32_llround_52549","line":47217,"operands":["[B1800096]"],"expected":"-2","status":"00","rounding":0},
    {"id":"bid32_llround_52550","line":47218,"operands":["[B1807562]"],"expected":"-301","status":"00","rounding":0},
    {"id":"bid32_llround_52551","line":47219,"operands":["[B2000005]"],"expected":"-1","status":"00","rounding":0},
    {"id":"bid32_llround_52552","line":47220,"operands":["[B200000F]"],"expected":"-2","status":"00","rounding":0},
    {"id":"bid32_llround_52553","line":47221,"operands":["[B2000BB8]"],"expected":"-300","status":"00","rounding":0},
    {"id":"bid32_llround_52554","line":47222,"operands":["[B2000BBD]"],"expected":"-301","status":"00","rounding":0},
    {"id":"bid32_llround_52555","line":47223,"operands":["[B2800001]"],"expected":"-1","status":"00","rounding":0},
    {"id":"bid32_llround_52556","line":47224,"operands":["[B280012C]"],"expected":"-300","status":"00","rounding":0},
    {"id":"bid32_llround_52557","line":47225,"operands":["[B300001E]"],"expected":"-300","status":"00","rounding":0},
    {"id":"bid32_llround_52558","line":47226,"operands":["[B3800003]"],"expected":"-300","status":"00","rounding":0},
    {"id":"bid32_llround_52559","line":47227,"operands":["[B420C49C]"],"expected":"-2147484000","status":"00","rounding":0},
    {"id":"bid32_llround_52560","line":47228,"operands":["[B43D0900]"],"expected":"-4000000000","status":"00","rounding":0},
    {"id":"bid32_llround_52561","line":47229,"operands":["[B4418937]"],"expected":"-4294967000","status":"00","rounding":0},
    {"id":"bid32_llround_52562","line":47230,"operands":["[B44C4B40]"],"expected":"-5000000000","status":"00","rounding":0},
    {"id":"bid32_llround_52563","line":47231,"operands":["[B49E8480]"],"expected":"-20000000000","status":"00","rounding":0},
    {"id":"bid32_llround_52564","line":47232,"operands":["[B7000004]"],"expected":"-4000000000","status":"00","rounding":0},
    {"id":"bid32_llround_52565","line":47233,"operands":["[B7000005]"],"expected":"-5000000000","status":"00","rounding":0},
    {"id":"bid32_llround_52566","line":47234,"operands":["[B71E8480]"],"expected":"-2000000000000000","status":"00","rounding":0},
    {"id":"bid32_llround_52567","line":47235,"operands":["[B7800002]"],"expected":"-20000000000","status":"00","rounding":0},
    {"id":"bid32_llround_52568","line":47236,"operands":["[B90F4240]"],"expected":"-9223372036854775808","status":"01","rounding":0},
    {"id":"bid32_llround_52569","line":47237,"operands":["[B90F4240]"],"expected":"-9223372036854775808","status":"01","rounding":0},
    {"id":"bid32_llround_52570","line":47238,"operands":["[B916E360]"],"expected":"-9223372036854775808","status":"01","rounding":0},
    {"id":"bid32_llround_52571","line":47239,"operands":["[B91C25C2]"],"expected":"-9223372036854775808","status":"01","rounding":0},
    {"id":"bid32_llround_52572","line":47240,"operands":["[B91E8480]"],"expected":"-9223372036854775808","status":"01","rounding":0},
    {"id":"bid32_llround_52573","line":47241,"operands":["[B92625A0]"],"expected":"-9223372036854775808","status":"01","rounding":0},
    {"id":"bid32_llround_52574","line":47242,"operands":["[B98F4240]"],"expected":"-9223372036854775808","status":"01","rounding":0},
    {"id":"bid32_llround_52575","line":47243,"operands":["[BA000002]"],"expected":"-2000000000000000","status":"00","rounding":0},
    {"id":"bid32_llround_52576","line":47244,"operands":["[BB80000F]"],"expected":"-9223372036854775808","status":"01","rounding":0},
    {"id":"bid32_llround_52577","line":47245,"operands":["[BB800019]"],"expected":"-9223372036854775808","status":"01","rounding":0},
    {"id":"bid32_llround_52578","line":47246,"operands":["[BC000001]"],"expected":"-9223372036854775808","status":"01","rounding":0},
    {"id":"bid32_llround_52579","line":47247,"operands":["[BC000002]"],"expected":"-9223372036854775808","status":"01","rounding":0},
    {"id":"bid32_llround_52580","line":47248,"operands":["[BC800001]"],"expected":"-9223372036854775808","status":"01","rounding":0},
    {"id":"bid32_llround_52581","line":47249,"operands":["[EBD86F70]"],"expected":"-1","status":"00","rounding":0},
    {"id":"bid32_llround_52582","line":47250,"operands":["[EE2CBCCC]"],"expected":"-9223372000000000000","status":"00","rounding":0}
  ]
}
