{
  "suite": "bid32_modf",
  "group": "decimal32_operations",
  "format": "decimal32",
  "header": "third_party/intel_dfp/TESTS/readtest.h",
  "source": "third_party/intel_dfp/TESTS/readtest.in",
  "function": "bid32_modf",
  "kind": "binary_op",
  "output_type": "OP_DEC32",
  "input_types": [
    "OP_DEC32",
    "OP_DEC32"
  ],
  "compare_group": "CMP_FUZZYSTATUS",
  "cases": [
    {"id":"bid32_modf_78185","line":50100,"operands":["[7c000000]","[7c000000]"],"expected":"[7c000000]","status":"00","rounding":0},
    {"id":"bid32_modf_78186","line":50101,"operands":["[7e000000]","[7c000000]"],"expected":"[7c000000]","status":"01","rounding":0},
    {"id":"bid32_modf_78187","line":50102,"operands":["[fc000000]","[fc000000]"],"expected":"[fc000000]","status":"00","rounding":0},
    {"id":"bid32_modf_78188","line":50103,"operands":["[fe000000]","[fc000000]"],"expected":"[fc000000]","status":"01","rounding":0},
    {"id":"bid32_modf_78189","line":93132,"operands":["[2F8F4241]","[32800001]"],"expected":"[2F800001]","status":"00","rounding":0},
    {"id":"bid32_modf_78190","line":93133,"operands":["[AF8F4241]","[B2800001]"],"expected":"[AF800001]","status":"00","rounding":0},
    {"id":"bid32_modf_78191","line":93134,"operands":["[2F8F4241]","[32800001]"],"expected":"[2F800001]","status":"00","rounding":1},
    {"id":"bid32_modf_78192","line":93135,"operands":["[AF8F4241]","[B2800001]"],"expected":"[AF800001]","status":"00","rounding":1},
    {"id":"bid32_modf_78193","line":93136,"operands":["[2F8F4241]","[32800001]"],"expected":"[2F800001]","status":"00","rounding":2},
    {"id":"bid32_modf_78194","line":93137,"operands":["[AF8F4241]","[B2800001]"],"expected":"[AF800001]","status":"00","rounding":2},
    {"id":"bid32_modf_78195","line":93138,"operands":["[2F8F4241]","[32800001]"],"expected":"[2F800001]","status":"00","rounding":3},
    {"id":"bid32_modf_78196","line":93139,"operands":["[AF8F4241]","[B2800001]"],"expected":"[AF800001]","status":"00","rounding":3},
    {"id":"bid32_modf_78197","line":94224,"operands":["[00000001]","[32800000]"],"expected":"[00000001]","status":"00","rounding":0},
    {"id":"bid32_modf_78198","line":94225,"operands":["[000F423F]","[32800000]"],"expected":"[000F423F]","status":"00","rounding":0},
    {"id":"bid32_modf_78199","line":94226,"operands":["[000F4240]","[32800000]"],"expected":"[000F4240]","status":"00","rounding":0},
    {"id":"bid32_modf_78200","line":94227,"operands":["[000F4241]","[32800000]"],"expected":"[000F4241]","status":"00","rounding":0},
    {"id":"bid32_modf_78201","line":94228,"operands":["[6BD8967F]","[32800000]"],"expected":"[6BD8967F]","status":"00","rounding":0},
    {"id":"bid32_modf_78202","line":94229,"operands":["[77F8967F]","[77F8967F]"],"expected":"[5f800000]","status":"00","rounding":0},
    {"id":"bid32_modf_78203","line":94230,"operands":["[78000000]","[78000000]"],"expected":"[5f800000]","status":"00","rounding":0},
    {"id":"bid32_modf_78204","line":94231,"operands":["[80000001]","[b2800000]"],"expected":"[80000001]","status":"00","rounding":0},
    {"id":"bid32_modf_78205","line":94232,"operands":["[800F423F]","[b2800000]"],"expected":"[800F423F]","status":"00","rounding":0},
    {"id":"bid32_modf_78206","line":94233,"operands":["[800F4240]","[b2800000]"],"expected":"[800F4240]","status":"00","rounding":0},
    {"id":"bid32_modf_78207","line":94234,"operands":["[800F4241]","[b2800000]"],"expected":"[800F4241]","status":"00","rounding":0},
    {"id":"bid32_modf_78208","line":94235,"operands":["[EBD8967F]","[b2800000]"],"expected":"[EBD8967F]","status":"00","rounding":0},
    {"id":"bid32_modf_78209","line":94236,"operands":["[F7F8967F]","[F7F8967F]"],"expected":"[df800000]","status":"00","rounding":0},
    {"id":"bid32_modf_78210","line":94237,"operands":["[f8000000]","[f8000000]"],"expected":"[df800000]","status":"00","rounding":0},
    {"id":"bid32_modf_78211","line":94238,"operands":["[00000001]","[32800000]"],"expected":"[00000001]","status":"00","rounding":1},
    {"id":"bid32_modf_78212","line":94239,"operands":["[000F423F]","[32800000]"],"expected":"[000F423F]","status":"00","rounding":1},
    {"id":"bid32_modf_78213","line":94240,"operands":["[000F4240]","[32800000]"],"expected":"[000f4240]","status":"00","rounding":1},
    {"id":"bid32_modf_78214","line":94241,"operands":["[000F4241]","[32800000]"],"expected":"[000F4241]","status":"00","rounding":1},
    {"id":"bid32_modf_78215","line":94242,"operands":["[6BD8967F]","[32800000]"],"expected":"[6BD8967F]","status":"00","rounding":1},
    {"id":"bid32_modf_78216","line":94243,"operands":["[77F8967F]","[77F8967F]"],"expected":"[5f800000]","status":"00","rounding":1},
    {"id":"bid32_modf_78217","line":94244,"operands":["[80000001]","[b2800000]"],"expected":"[80000001]","status":"00","rounding":1},
    {"id":"bid32_modf_78218","line":94245,"operands":["[800F423F]","[b2800000]"],"expected":"[800F423F]","status":"00","rounding":1},
    {"id":"bid32_modf_78219","line":94246,"operands":["[800F4240]","[b2800000]"],"expected":"[800f4240]","status":"00","rounding":1},
    {"id":"bid32_modf_78220","line":94247,"operands":["[800F4241]","[b2800000]"],"expected":"[800F4241]","status":"00","rounding":1},
    {"id":"bid32_modf_78221","line":94248,"operands":["[EBD8967F]","[b2800000]"],"expected":"[EBD8967F]","status":"00","rounding":1},
    {"id":"bid32_modf_78222","line":94249,"operands":["[F7F8967F]","[F7F8967F]"],"expected":"[df800000]","status":"00","rounding":1},
    {"id":"bid32_modf_78223","line":94250,"operands":["[00000001]","[32800000]"],"expected":"[00000001]","status":"00","rounding":2},
    {"id":"bid32_modf_78224","line":94251,"operands":["[000F423F]","[32800000]"],"expected":"[000F423F]","status":"00","rounding":2},
    {"id":"bid32_modf_78225","line":94252,"operands":["[000F4240]","[32800000]"],"expected":"[000f4240]","status":"00","rounding":2},
    {"id":"bid32_modf_78226","line":94253,"operands":["[000F4241]","[32800000]"],"expected":"[000F4241]","status":"00","rounding":2},
    {"id":"bid32_modf_78227","line":94254,"operands":["[6BD8967F]","[32800000]"],"expected":"[6BD8967F]","status":"00","rounding":2},
    {"id":"bid32_modf_78228","line":94255,"operands":["[77F8967F]","[77F8967F]"],"expected":"[5f800000]","status":"00","rounding":2},
    {"id":"bid32_modf_78229","line":94256,"operands":["[80000001]","[b2800000]"],"expected":"[80000001]","status":"00","rounding":2},
    {"id":"bid32_modf_78230","line":94257,"operands":["[800F423F]","[b2800000]"],"expected":"[800F423F]","status":"00","rounding":2},
    {"id":"bid32_modf_78231","line":94258,"operands":["[800F4240]","[b2800000]"],"expected":"[800f4240]","status":"00","rounding":2},
    {"id":"bid32_modf_78232","line":94259,"operands":["[800F4241]","[b2800000]"],"expected":"[800F4241]","status":"00","rounding":2},
    {"id":"bid32_modf_78233","line":94260,"operands":["[EBD8967F]","[b2800000]"],"expected":"[EBD8967F]","status":"00","rounding":2},
    {"id":"bid32_modf_78234","line":94261,"operands":["[F7F8967F]","[F7F8967F]"],"expected":"[df800000]","status":"00","rounding":2},
    {"id":"bid32_modf_78235","line":94262,"operands":["[00000001]","[32800000]"],"expected":"[00000001]","status":"00","rounding":3},
    {"id":"bid32_modf_78236","line":94263,"operands":["[000F423F]","[32800000]"],"expected":"[000F423F]","status":"00","rounding":3},
    {"id":"bid32_modf_78237","line":94264,"operands":["[000F4240]","[32800000]"],"expected":"[000f4240]","status":"00","rounding":3},
    {"id":"bid32_modf_78238","line":94265,"operands":["[000F4241]","[32800000]"],"expected":"[000F4241]","status":"00","rounding":3},
    {"id":"bid32_modf_78239","line":94266,"operands":["[6BD8967F]","[32800000]"],"expected":"[6BD8967F]","status":"00","rounding":3},
    {"id":"bid32_modf_78240","line":94267,"operands":["[77F8967F]","[77F8967F]"],"expected":"[5f800000]","status":"00","rounding":3},
    {"id":"bid32_modf_78241","line":94268,"operands":["[80000001]","[b2800000]"],"expected":"[80000001]","status":"00","rounding":3},
    {"id":"bid32_modf_78242","line":94269,"operands":["[800F423F]","[b2800000]"],"expected":"[800F423F]","status":"00","rounding":3},
    {"id":"bid32_modf_78243","line":94270,"operands":["[800F4240]","[b2800000]"],"expected":"[800f4240]","status":"00","rounding":3},
    {"id":"bid32_modf_78244","line":94271,"operands":["[800F4241]","[b2800000]"],"expected":"[800F4241]","status":"00","rounding":3},
    {"id":"bid32_modf_78245","line":94272,"operands":["[EBD8967F]","[b2800000]"],"expected":"[EBD8967F]","status":"00","rounding":3},
    {"id":"bid32_modf_78246","line":94273,"operands":["[F7F8967F]","[F7F8967F]"],"expected":"[df800000]","status":"00","rounding":3}
  ]
}
