{
  "suite": "bid64_to_uint32_int",
  "group": "decimal64_operations",
  "format": "decimal64",
  "header": "third_party/intel_dfp/TESTS/readtest.h",
  "source": "third_party/intel_dfp/TESTS/readtest.in",
  "function": "bid64_to_uint32_int",
  "kind": "unary_op",
  "output_type": "OP_BID_UINT32",
  "input_types": [
    "OP_DEC64"
  ],
  "compare_group": "CMP_FUZZYSTATUS",
  "cases": [
    {"id":"bid64_to_uint32_int_17323","line":83507,"operands":["0"],"expected":"0","status":"00","rounding":0},
    {"id":"bid64_to_uint32_int_17324","line":83508,"operands":["-0.000E0"],"expected":"0","status":"00","rounding":0},
    {"id":"bid64_to_uint32_int_17325","line":83509,"operands":["[0100004030000050]"],"expected":"0","status":"00","rounding":0},
    {"id":"bid64_to_uint32_int_17326","line":83510,"operands":["[065d5f850dbf0596]"],"expected":"0","status":"00","rounding":0},
    {"id":"bid64_to_uint32_int_17327","line":83511,"operands":["[0be1015389fd700f]"],"expected":"0","status":"00","rounding":0},
    {"id":"bid64_to_uint32_int_17328","line":83512,"operands":["[0ef8000000000000]"],"expected":"0","status":"00","rounding":0},
    {"id":"bid64_to_uint32_int_17329","line":83513,"operands":["[0f83000000000000]"],"expected":"0","status":"00","rounding":0},
    {"id":"bid64_to_uint32_int_17330","line":83514,"operands":["[2912e034166b2a53]"],"expected":"0","status":"00","rounding":0},
    {"id":"bid64_to_uint32_int_17331","line":83515,"operands":["[2FD1C37937E08000]"],"expected":"0","status":"00","rounding":0},
    {"id":"bid64_to_uint32_int_17332","line":83517,"operands":["[2FE5543DF729C000]"],"expected":"1","status":"00","rounding":0},
    {"id":"bid64_to_uint32_int_17333","line":83518,"operands":["[300202403045a510]"],"expected":"5","status":"00","rounding":0},
    {"id":"bid64_to_uint32_int_17334","line":83520,"operands":["[302AAD08158CD000]"],"expected":"300","status":"00","rounding":0},
    {"id":"bid64_to_uint32_int_17335","line":83521,"operands":["[3107A11FFFE91CA0]"],"expected":"2147483646","status":"00","rounding":0},
    {"id":"bid64_to_uint32_int_17336","line":83522,"operands":["[3107A11FFFF0BDC0]"],"expected":"2147483647","status":"00","rounding":0},
    {"id":"bid64_to_uint32_int_17337","line":83523,"operands":["[3107A11FFFF85EE0]"],"expected":"2147483647","status":"00","rounding":0},
    {"id":"bid64_to_uint32_int_17338","line":83524,"operands":["[3107A12000000000]"],"expected":"2147483648","status":"00","rounding":0},
    {"id":"bid64_to_uint32_int_17339","line":83525,"operands":["[3107A1200007A120]"],"expected":"2147483648","status":"00","rounding":0},
    {"id":"bid64_to_uint32_int_17340","line":83526,"operands":["[3107A120000F4240]"],"expected":"2147483649","status":"00","rounding":0},
    {"id":"bid64_to_uint32_int_17341","line":83528,"operands":["[310F423FFFF0BDC0]"],"expected":"4294967295","status":"00","rounding":0},
    {"id":"bid64_to_uint32_int_17342","line":83529,"operands":["[310F423FFFF85EE0]"],"expected":"4294967295","status":"00","rounding":0},
    {"id":"bid64_to_uint32_int_17343","line":83530,"operands":["[310F424000000000]"],"expected":"2147483648","status":"01","rounding":0},
    {"id":"bid64_to_uint32_int_17344","line":83531,"operands":["[310F42400007A120]"],"expected":"2147483648","status":"01","rounding":0},
    {"id":"bid64_to_uint32_int_17345","line":83532,"operands":["[310F4240000F4240]"],"expected":"2147483648","status":"01","rounding":0},
    {"id":"bid64_to_uint32_int_17346","line":83534,"operands":["[311cf32120d60503]"],"expected":"2147483648","status":"01","rounding":0},
    {"id":"bid64_to_uint32_int_17347","line":83535,"operands":["[31271AFD498AB610]"],"expected":"2147483648","status":"01","rounding":0},
    {"id":"bid64_to_uint32_int_17348","line":83536,"operands":["[31271AFD498B7960]"],"expected":"2147483648","status":"01","rounding":0},
    {"id":"bid64_to_uint32_int_17349","line":83537,"operands":["[31271AFD498C3CB0]"],"expected":"2147483648","status":"01","rounding":0},
    {"id":"bid64_to_uint32_int_17350","line":83539,"operands":["[31271AFD498DC350]"],"expected":"2147483648","status":"01","rounding":0},
    {"id":"bid64_to_uint32_int_17351","line":83540,"operands":["[31271AFD498E86A0]"],"expected":"2147483648","status":"01","rounding":0},
    {"id":"bid64_to_uint32_int_17352","line":83541,"operands":["[31271AFD498F49F0]"],"expected":"2147483648","status":"01","rounding":0},
    {"id":"bid64_to_uint32_int_17353","line":83542,"operands":["[31600000000003E7]"],"expected":"0","status":"00","rounding":0},
    {"id":"bid64_to_uint32_int_17354","line":83543,"operands":["[31A0000000000005]"],"expected":"0","status":"00","rounding":0},
    {"id":"bid64_to_uint32_int_17355","line":83544,"operands":["[31A000000000000F]"],"expected":"1","status":"00","rounding":0},
    {"id":"bid64_to_uint32_int_17356","line":83545,"operands":["[31A0000000000BBD]"],"expected":"300","status":"00","rounding":0},
    {"id":"bid64_to_uint32_int_17357","line":83546,"operands":["[31A00004FFFFFFF1]"],"expected":"2147483646","status":"00","rounding":0},
    {"id":"bid64_to_uint32_int_17358","line":83547,"operands":["[31A00004FFFFFFFB]"],"expected":"2147483647","status":"00","rounding":0},
    {"id":"bid64_to_uint32_int_17359","line":83548,"operands":["[31A0000500000005]"],"expected":"2147483648","status":"00","rounding":0},
    {"id":"bid64_to_uint32_int_17360","line":83549,"operands":["[31A00009FFFFFFFB]"],"expected":"4294967295","status":"00","rounding":0},
    {"id":"bid64_to_uint32_int_17361","line":83550,"operands":["[31A0000A00000005]"],"expected":"2147483648","status":"01","rounding":0},
    {"id":"bid64_to_uint32_int_17362","line":83551,"operands":["[31A0002E90EDCFF1]"],"expected":"2147483648","status":"01","rounding":0},
    {"id":"bid64_to_uint32_int_17363","line":83552,"operands":["[31A0002E90EDCFFB]"],"expected":"2147483648","status":"01","rounding":0},
    {"id":"bid64_to_uint32_int_17364","line":83553,"operands":["[31A0002E90EDD005]"],"expected":"2147483648","status":"01","rounding":0},
    {"id":"bid64_to_uint32_int_17365","line":83554,"operands":["[31A0002E90EDD00F]"],"expected":"2147483648","status":"01","rounding":0},
    {"id":"bid64_to_uint32_int_17366","line":83556,"operands":["[31c000001e028000]"],"expected":"503480320","status":"00","rounding":0},
    {"id":"bid64_to_uint32_int_17367","line":83557,"operands":["[31C000007FFFFFFF]"],"expected":"2147483647","status":"00","rounding":0},
    {"id":"bid64_to_uint32_int_17368","line":83558,"operands":["[31C0000080000000]"],"expected":"2147483648","status":"00","rounding":0},
    {"id":"bid64_to_uint32_int_17369","line":83559,"operands":["[31C0000080000001]"],"expected":"2147483649","status":"00","rounding":0},
    {"id":"bid64_to_uint32_int_17370","line":83560,"operands":["[31C00000FFFFFFFF]"],"expected":"4294967295","status":"00","rounding":0},
    {"id":"bid64_to_uint32_int_17371","line":83561,"operands":["[31C0000100000000]"],"expected":"2147483648","status":"01","rounding":0},
    {"id":"bid64_to_uint32_int_17372","line":83562,"operands":["[31C0000100000001]"],"expected":"2147483648","status":"01","rounding":0},
    {"id":"bid64_to_uint32_int_17373","line":83563,"operands":["[31C00004A817C7FF]"],"expected":"2147483648","status":"01","rounding":0},
    {"id":"bid64_to_uint32_int_17374","line":83564,"operands":["[31C00004A817C801]"],"expected":"2147483648","status":"01","rounding":0},
    {"id":"bid64_to_uint32_int_17375","line":83566,"operands":["[32000000000000a0]"],"expected":"16000","status":"00","rounding":0},
    {"id":"bid64_to_uint32_int_17376","line":83567,"operands":["[3200000004010084]"],"expected":"2147483648","status":"01","rounding":0},
    {"id":"bid64_to_uint32_int_17377","line":83571,"operands":["[3c0bc042e540295f]"],"expected":"2147483648","status":"01","rounding":0},
    {"id":"bid64_to_uint32_int_17378","line":83572,"operands":["[3f00000000000000]"],"expected":"0","status":"00","rounding":0},
    {"id":"bid64_to_uint32_int_17379","line":83573,"operands":["[43c075645356b2e2]"],"expected":"2147483648","status":"01","rounding":0},
    {"id":"bid64_to_uint32_int_17380","line":83574,"operands":["[556703de2b973296]"],"expected":"2147483648","status":"01","rounding":0},
    {"id":"bid64_to_uint32_int_17381","line":83575,"operands":["[68b77d4bed1ad8ea]"],"expected":"0","status":"00","rounding":0},
    {"id":"bid64_to_uint32_int_17382","line":83576,"operands":["[6BF37DDA214E6000]"],"expected":"0","status":"00","rounding":0},
    {"id":"bid64_to_uint32_int_17383","line":83577,"operands":["[6C7386F26FC10000]"],"expected":"0","status":"00","rounding":0},
    {"id":"bid64_to_uint32_int_17384","line":83578,"operands":["[7800000000000000]"],"expected":"2147483648","status":"01","rounding":0},
    {"id":"bid64_to_uint32_int_17385","line":83579,"operands":["[7c00000000000000]"],"expected":"2147483648","status":"01","rounding":0},
    {"id":"bid64_to_uint32_int_17386","line":83580,"operands":["[7e00000000000000]"],"expected":"2147483648","status":"01","rounding":0},
    {"id":"bid64_to_uint32_int_17387","line":83581,"operands":["[94e150e3ea62a117]"],"expected":"0","status":"00","rounding":0},
    {"id":"bid64_to_uint32_int_17388","line":83582,"operands":["[b121c11a7dcedba4]"],"expected":"2147483648","status":"01","rounding":0},
    {"id":"bid64_to_uint32_int_17389","line":83583,"operands":["[b26a545ba441bc82]"],"expected":"2147483648","status":"01","rounding":0},
    {"id":"bid64_to_uint32_int_17390","line":83584,"operands":["[b4921dff9a0cb0c4]"],"expected":"2147483648","status":"01","rounding":0},
    {"id":"bid64_to_uint32_int_17391","line":83585,"operands":["[ec29a14e9fab44aa]"],"expected":"2147483648","status":"01","rounding":0},
    {"id":"bid64_to_uint32_int_17392","line":83586,"operands":["[f5226d1a9ccc49d0]"],"expected":"2147483648","status":"01","rounding":0},
    {"id":"bid64_to_uint32_int_17393","line":83587,"operands":["-Infinity"],"expected":"2147483648","status":"01","rounding":0},
    {"id":"bid64_to_uint32_int_17394","line":83588,"operands":["Infinity"],"expected":"2147483648","status":"01","rounding":0},
    {"id":"bid64_to_uint32_int_17395","line":83590,"operands":["SNaN"],"expected":"2147483648","status":"01","rounding":0}
  ]
}
